operationprimos/__init__.py
operationprimos-1.0.dist-info/LICENSE
operationprimos-1.0.dist-info/METADATA
operationprimos-1.0.dist-info/WHEEL
operationprimos-1.0.dist-info/top_level.txt
operationprimos-1.0.dist-info/RECORD
